{
    "difficulty": "beginner",
    "visualizerParams": {
        "visualizerType": "CodeRefactorChallenge",
        "visualizerParams": {
            "title": "Code Refactor: Switch Expressions",
            "problemDescription": "Refactor the old switch statement to a modern Java 14+ switch expression.",
            "language": "java",
            "initialCode": "public class SwitchBreak {\n    public static void main(String[] args) {\n        int day = 2;\n        String name;\n        switch (day) {\n            case 1:\n                name = \"Monday\";\n                break;\n            case 2:\n                name = \"Tuesday\";\n                break;\n            default:\n                name = \"Unknown\";\n        }\n        System.out.println(name);\n    }\n}",
            "solution": {
                "code": "public class SwitchBreak {\n    public static void main(String[] args) {\n        int day = 2;\n        String name = switch (day) {\n            case 1 -> \"Monday\";\n            case 2 -> \"Tuesday\";\n            default -> \"Unknown\";\n        };\n        System.out.println(name);\n    }\n}",
                "explanation": "Switch expressions are more concise, can return a value directly, and eliminate the need for the 'break' keyword."
            },
            "validation": {
                "type": "run_code"
            }
        }
    }
}